LICENSE
raphaelbarreiros_psa_car_controller/__init__.py
raphaelbarreiros_psa_car_controller/__main__.py
raphaelbarreiros_psa_car_controller/common/__init__.py
raphaelbarreiros_psa_car_controller/common/mylogger.py
raphaelbarreiros_psa_car_controller/common/utils.py
raphaelbarreiros_psa_car_controller/psa/AccountInformation.py
raphaelbarreiros_psa_car_controller/psa/RemoteClient.py
raphaelbarreiros_psa_car_controller/psa/RemoteCredentials.py
raphaelbarreiros_psa_car_controller/psa/__init__.py
raphaelbarreiros_psa_car_controller/psa/connected_car_api/__init__.py
raphaelbarreiros_psa_car_controller/psa/connected_car_api/api/__init__.py
raphaelbarreiros_psa_car_controller/psa/connected_car_api/api/trips_api.py
raphaelbarreiros_psa_car_controller/psa/connected_car_api/api/user_api.py
raphaelbarreiros_psa_car_controller/psa/connected_car_api/api/vehicles_api.py
raphaelbarreiros_psa_car_controller/psa/connected_car_api/api_client.py
raphaelbarreiros_psa_car_controller/psa/connected_car_api/configuration.py
raphaelbarreiros_psa_car_controller/psa/connected_car_api/models/__init__.py
raphaelbarreiros_psa_car_controller/psa/connected_car_api/models/adas.py
raphaelbarreiros_psa_car_controller/psa/connected_car_api/models/adas_park_assist.py
raphaelbarreiros_psa_car_controller/psa/connected_car_api/models/alert.py
raphaelbarreiros_psa_car_controller/psa/connected_car_api/models/alert_end_position.py
raphaelbarreiros_psa_car_controller/psa/connected_car_api/models/alert_links.py
raphaelbarreiros_psa_car_controller/psa/connected_car_api/models/alert_msg_enum.py
raphaelbarreiros_psa_car_controller/psa/connected_car_api/models/alerts.py
raphaelbarreiros_psa_car_controller/psa/connected_car_api/models/alerts_embedded.py
raphaelbarreiros_psa_car_controller/psa/connected_car_api/models/battery.py
raphaelbarreiros_psa_car_controller/psa/connected_car_api/models/bounded_program.py
raphaelbarreiros_psa_car_controller/psa/connected_car_api/models/charging_status_enum.py
raphaelbarreiros_psa_car_controller-3.5.11.dist-info/LICENSE
raphaelbarreiros_psa_car_controller-3.5.11.dist-info/METADATA
raphaelbarreiros_psa_car_controller-3.5.11.dist-info/WHEEL
raphaelbarreiros_psa_car_controller-3.5.11.dist-info/entry_points.txt
raphaelbarreiros_psa_car_controller-3.5.11.dist-info/RECORD
